bitsandbytes/__init__.py
bitsandbytes/__main__.py
bitsandbytes/_ops.py
bitsandbytes/cextension.py
bitsandbytes/consts.py
bitsandbytes/cuda_specs.py
bitsandbytes/functional.py
bitsandbytes/libbitsandbytes_cpu.dll
bitsandbytes/libbitsandbytes_cuda118.dll
bitsandbytes/libbitsandbytes_cuda120.dll
bitsandbytes/libbitsandbytes_cuda121.dll
bitsandbytes/libbitsandbytes_cuda122.dll
bitsandbytes/libbitsandbytes_cuda123.dll
bitsandbytes/libbitsandbytes_cuda124.dll
bitsandbytes/libbitsandbytes_cuda125.dll
bitsandbytes/libbitsandbytes_cuda126.dll
bitsandbytes/libbitsandbytes_cuda128.dll
bitsandbytes/libbitsandbytes_cuda129.dll
bitsandbytes/libbitsandbytes_cuda130.dll
bitsandbytes/libbitsandbytes_xpu.dll
bitsandbytes/py.typed
bitsandbytes/utils.py
bitsandbytes/autograd/__init__.py
bitsandbytes/autograd/_functions.py
bitsandbytes/backends/__init__.py
bitsandbytes/backends/utils.py
bitsandbytes/backends/cpu/__init__.py
bitsandbytes/backends/cpu/ops.py
bitsandbytes/backends/cuda/__init__.py
bitsandbytes/backends/cuda/ops.py
bitsandbytes/backends/default/__init__.py
bitsandbytes/backends/default/ops.py
bitsandbytes/backends/hpu/__init__.py
bitsandbytes/backends/hpu/ops.py
bitsandbytes/backends/triton/__init__.py
bitsandbytes/backends/triton/kernels_4bit.py
bitsandbytes/backends/triton/kernels_8bit_quant.py
bitsandbytes/backends/triton/kernels_optim.py
bitsandbytes/backends/triton/ops.py
bitsandbytes/backends/xpu/__init__.py
bitsandbytes/backends/xpu/ops.py
bitsandbytes/diagnostics/__init__.py
bitsandbytes/diagnostics/cuda.py
bitsandbytes/diagnostics/main.py
bitsandbytes/diagnostics/utils.py
bitsandbytes/nn/__init__.py
bitsandbytes/nn/modules.py
bitsandbytes/nn/parametrize.py
bitsandbytes/nn/triton_based_modules.py
bitsandbytes/optim/__init__.py
bitsandbytes/optim/adagrad.py
bitsandbytes/optim/adam.py
bitsandbytes/optim/adamw.py
bitsandbytes/optim/ademamix.py
bitsandbytes/optim/lamb.py
bitsandbytes/optim/lars.py
bitsandbytes/optim/lion.py
bitsandbytes/optim/optimizer.py
bitsandbytes-0.49.1.dist-info/licenses/LICENSE
bitsandbytes-0.49.1.dist-info/METADATA
bitsandbytes-0.49.1.dist-info/WHEEL
bitsandbytes-0.49.1.dist-info/top_level.txt
bitsandbytes-0.49.1.dist-info/RECORD
