Metadata-Version: 2.4
Name: bitsandbytes
Version: 0.49.1
Summary: k-bit optimizers and matrix multiplication routines.
Author-email: Tim Dettmers <dettmers@cs.washington.edu>
Maintainer-email: Titus von Köller <titus@huggingface.co>, Matthew Douglas <matthew.douglas@huggingface.co>
License-Expression: MIT
Project-URL: homepage, https://github.com/bitsandbytes-foundation/bitsandbytes
Project-URL: changelog, https://github.com/bitsandbytes-foundation/bitsandbytes/blob/main/CHANGELOG.md
Project-URL: docs, https://huggingface.co/docs/bitsandbytes/main
Project-URL: issues, https://github.com/bitsandbytes-foundation/bitsandbytes/issues
Keywords: gpu,optimizers,optimization,8-bit,quantization,compression
Classifier: Development Status :: 4 - Beta
Classifier: Environment :: GPU :: NVIDIA CUDA :: 11.8
Classifier: Environment :: GPU :: NVIDIA CUDA :: 12
Classifier: Environment :: GPU :: NVIDIA CUDA :: 13
Classifier: Intended Audience :: Developers
Classifier: Intended Audience :: Science/Research
Classifier: Operating System :: POSIX :: Linux
Classifier: Operating System :: MacOS
Classifier: Operating System :: Microsoft :: Windows
Classifier: Programming Language :: C++
Classifier: Programming Language :: Python :: Implementation :: CPython
Classifier: Programming Language :: Python :: 3.10
Classifier: Programming Language :: Python :: 3.11
Classifier: Programming Language :: Python :: 3.12
Classifier: Programming Language :: Python :: 3.13
Classifier: Programming Language :: Python :: 3.14
Classifier: Topic :: Scientific/Engineering :: Artificial Intelligence
Requires-Python: >=3.10
License-File: LICENSE
Requires-Dist: torch<3,>=2.3
Requires-Dist: numpy>=1.17
Requires-Dist: packaging>=20.9
Provides-Extra: benchmark
Requires-Dist: pandas; extra == "benchmark"
Requires-Dist: matplotlib; extra == "benchmark"
Provides-Extra: docs
Requires-Dist: hf-doc-builder==0.5.0; extra == "docs"
Provides-Extra: dev
Requires-Dist: bitsandbytes[test]; extra == "dev"
Requires-Dist: build<2,>=1.0.0; extra == "dev"
Requires-Dist: ruff~=0.14.3; extra == "dev"
Requires-Dist: pre-commit<4,>=3.5.0; extra == "dev"
Requires-Dist: wheel<1,>=0.42; extra == "dev"
Provides-Extra: test
Requires-Dist: einops~=0.8.0; extra == "test"
Requires-Dist: lion-pytorch==0.2.3; extra == "test"
Requires-Dist: pytest~=8.3; extra == "test"
Requires-Dist: scipy<2,>=1.11.4; extra == "test"
Requires-Dist: transformers<5,>=4.30.1; extra == "test"
Dynamic: license-file
